BeginnersbookJavaZifuchuanJiaochengChuyiFix1/README.md
BeginnersbookJavaZifuchuanJiaochengChuyiFix1/__init__.py
BeginnersbookJavaZifuchuanJiaochengChuyiFix1/__main__.py
BeginnersbookJavaZifuchuanJiaochengChuyiFix1/file.epub
BeginnersbookJavaZifuchuanJiaochengChuyiFix1/index.html
BeginnersbookJavaZifuchuanJiaochengChuyiFix1/css/__init__.py
BeginnersbookJavaZifuchuanJiaochengChuyiFix1/css/annotations.css
BeginnersbookJavaZifuchuanJiaochengChuyiFix1/css/main.css
BeginnersbookJavaZifuchuanJiaochengChuyiFix1/css/normalize.css
BeginnersbookJavaZifuchuanJiaochengChuyiFix1/css/popup.css
BeginnersbookJavaZifuchuanJiaochengChuyiFix1/font/__init__.py
BeginnersbookJavaZifuchuanJiaochengChuyiFix1/font/fontello.eot
BeginnersbookJavaZifuchuanJiaochengChuyiFix1/font/fontello.svg
BeginnersbookJavaZifuchuanJiaochengChuyiFix1/font/fontello.ttf
BeginnersbookJavaZifuchuanJiaochengChuyiFix1/font/fontello.woff
BeginnersbookJavaZifuchuanJiaochengChuyiFix1/img/__init__.py
BeginnersbookJavaZifuchuanJiaochengChuyiFix1/img/annotator-glyph-sprite.png
BeginnersbookJavaZifuchuanJiaochengChuyiFix1/img/annotator-icon-sprite.png
BeginnersbookJavaZifuchuanJiaochengChuyiFix1/img/apple-touch-icon.png
BeginnersbookJavaZifuchuanJiaochengChuyiFix1/img/cancelfullscreen.png
BeginnersbookJavaZifuchuanJiaochengChuyiFix1/img/close.png
BeginnersbookJavaZifuchuanJiaochengChuyiFix1/img/fullscreen.png
BeginnersbookJavaZifuchuanJiaochengChuyiFix1/img/loader.gif
BeginnersbookJavaZifuchuanJiaochengChuyiFix1/img/menu-icon.png
BeginnersbookJavaZifuchuanJiaochengChuyiFix1/img/save.png
BeginnersbookJavaZifuchuanJiaochengChuyiFix1/img/saved.png
BeginnersbookJavaZifuchuanJiaochengChuyiFix1/img/settings-s.png
BeginnersbookJavaZifuchuanJiaochengChuyiFix1/img/settings.png
BeginnersbookJavaZifuchuanJiaochengChuyiFix1/img/star.png
BeginnersbookJavaZifuchuanJiaochengChuyiFix1/js/__init__.py
BeginnersbookJavaZifuchuanJiaochengChuyiFix1/js/epub.js
BeginnersbookJavaZifuchuanJiaochengChuyiFix1/js/epub.min.js
beginnersbook_java_zifuchuan_jiaocheng_chuyi_fix1-2025.3.24.1.dist-info/METADATA
beginnersbook_java_zifuchuan_jiaocheng_chuyi_fix1-2025.3.24.1.dist-info/WHEEL
beginnersbook_java_zifuchuan_jiaocheng_chuyi_fix1-2025.3.24.1.dist-info/entry_points.txt
beginnersbook_java_zifuchuan_jiaocheng_chuyi_fix1-2025.3.24.1.dist-info/top_level.txt
beginnersbook_java_zifuchuan_jiaocheng_chuyi_fix1-2025.3.24.1.dist-info/RECORD
